{
  "slug": "count-cells-between-two-values",
  "title": "How to count cells between two values",
  "task": "Count how many numbers fall inside a range, like between 10 and 20.",
  "keywords": [
    "countif between two numbers",
    "count values in range excel",
    "countifs between google sheets",
    "count within bounds"
  ],
  "solutions": {
    "excel": {
      "formula": "=COUNTIFS(A2:A6,\">=10\",A2:A6,\"<=20\")",
      "note": "Both conditions on the same range. Use \">\" / \"<\" for exclusive bounds."
    },
    "google_sheets": {
      "formula": "=COUNTIFS(A2:A6,\">=10\",A2:A6,\"<=20\")",
      "note": "Identical."
    },
    "libreoffice": {
      "formula": "=COUNTIFS(A2:A6,\">=10\",A2:A6,\"<=20\")",
      "note": "Identical."
    }
  },
  "verify": {
    "setup_cells": {
      "A2": 5,
      "A3": 12,
      "A4": 20,
      "A5": 25,
      "A6": 15
    },
    "formula": "=COUNTIFS(A2:A6,\">=10\",A2:A6,\"<=20\")",
    "expected": 3
  },
  "explanation": "A \"between\" count is just two conditions on the same range: at least 10 AND at most 20. Here 12, 20 and 15 qualify while 5 and 25 fall outside — count 3. To reference cells for the bounds, concatenate: =COUNTIFS(A2:A6,\">=\"&C1,A2:A6,\"<=\"&C2). SUMIFS/AVERAGEIFS take the same pattern for summing or averaging a band."
}
