{
  "slug": "count-cells-containing-text",
  "title": "How to count cells that contain specific text",
  "task": "Count cells that include a word anywhere in them, not just cells that equal it exactly.",
  "keywords": ["count cells containing text excel", "countif contains google sheets", "countif wildcard partial match", "count cells that contain a word"],
  "solutions": {
    "excel": {"formula": "=COUNTIF(A2:A6,\"*apple*\")", "note": "The * wildcards match any characters before and after 'apple'."},
    "google_sheets": {"formula": "=COUNTIF(A2:A6,\"*apple*\")", "note": "Identical."},
    "libreoffice": {"formula": "=COUNTIF(A2:A6,\"*apple*\")", "note": "Identical (wildcards enabled by default)."}
  },
  "verify": {"setup_cells": {"A2": "green apple", "A3": "banana", "A4": "apple pie", "A5": "cherry", "A6": "pineapple"}, "formula": "=COUNTIF(A2:A6,\"*apple*\")", "expected": 3},
  "explanation": "Wrapping the search term in asterisks (\"*apple*\") makes COUNTIF match any cell that contains 'apple' anywhere. 'green apple', 'apple pie' and 'pineapple' all match, so the count is 3. Use \"apple*\" to match only cells that start with apple."
}
